{
  "62": [
    [
      {
        "context": [
          {
            "name": "call_result",
            "value": 0
          },
          {
            "name": "us",
            "value": -302215120
          },
          {
            "name": "retval",
            "value": -302219080
          },
          {
            "name": "ret",
            "value": -1
          }
        ],
        "value": {
          "name": "angelic",
          "value": false
        },
        "expression": "911-6-911-42",
        "instId": 0
      }
    ]
  ]
}