{
  "file": "/angelix-experiments/.angelix/statistics.json",
  "src": "UNKNOWN",
  "buggy": "UNKNOWN",
  "patch_found": false,
  "patch_file": "UNKNOWN",
  "config": {
    "initial_tests": 1,
    "all_tests": false,
    "max_z3_trials": 2,
    "defect": [
      "if-conditions",
      "loop-conditions"
    ],
    "klee_out_dir_timeout": 5,
    "test_timeout": 60,
    "single_group": false,
    "group_size": 1,
    "group_by_score": false,
    "localize_from_bottom": false,
    "suspicious": 30,
    "localization": "jaccard",
    "ignore_trivial": false,
    "path_solving_timeout": 60000,
    "timeout": 14400,
    "max_angelic_paths": null,
    "klee_max_forks": null,
    "klee_max_depth": null,
    "klee_search": null,
    "klee_timeout": null,
    "klee_solver_timeout": null,
    "klee_debug": false,
    "klee_ignore_errors": false,
    "ignore_trans_errors": false,
    "ignore_infer_errors": false,
    "skip_validating_angelic_path": false,
    "use_nsynth": false,
    "use_osynth": false,
    "synthesis_timeout": 30000,
    "synthesis_levels": [
      "alternatives",
      "integer-constants",
      "boolean-constants"
    ],
    "synthesis_global_vars": false,
    "synthesis_func_params": false,
    "synthesis_used_vars": true,
    "synthesis_ptr_vars": false,
    "synthesis_bool_only": false,
    "empty_env_exps": false,
    "exclude_member_exp": false,
    "generate_all": false,
    "init_uninit_vars": false,
    "redundant_test": false,
    "verbose": false,
    "build_before_instr": false,
    "instr_printf": null,
    "mute_config_message": false,
    "mute_build_message": false,
    "mute_test_message": false,
    "show_test_message": false,
    "show_oracle_contents": false,
    "show_syn_message": false,
    "mute_warning": false,
    "show_suspicious_locations": true,
    "invalid_localization": false,
    "angelic_search_strategy": "guided",
    "step_method": "metropolis",
    "compilation_db_file": null,
    "keep_angelix_dir": false,
    "skip_configure": false,
    "skip_build": false,
    "gobble_klee_message": false,
    "lines": null,
    "search_max_trials": 100,
    "max_same_cost_iter": 20,
    "mcmc_beta": 0.8,
    "one_bit_flip_prob": 0.5,
    "chunk_bits": 32,
    "max_resample": 3,
    "block_expand_factor": 2,
    "inc_fix": false,
    "default_max_cost": 300000000.0,
    "error_cost": "10000000",
    "warning_cost": "5000000",
    "max_syn_attempts": 2,
    "max_repair_attempts": 2,
    "penalty1": "4",
    "penalty2": "2",
    "parallel_testing": false,
    "all_suspicious": true,
    "mutate": 0,
    "epsilon": 1.0,
    "always_accept": false,
    "skip_dd": false,
    "finish_after_fault_localize": false,
    "default_susp_score": 0.5,
    "additional_susp_locs": null,
    "default_non_zero_cost": "300000000",
    "timeout_cost": "1"
  },
  "time": {
    "testing": 121.00147700309753,
    "compilation": 64.91485476493835,
    "klee": 0,
    "synthesis": 0,
    "solving": 0,
    "inference": 119.97646403312683,
    "dd": 0,
    "total": 260.7383234500885
  },
  "iterations": {
    "synthesis": [],
    "guided": [
      {
        "locations": [
          [
            "I",
            [
              94,
              6,
              94,
              23
            ]
          ]
        ],
        "test": "3",
        "time": {
          "mcmc": 4.034890651702881,
          "dd": 0
        },
        "paths": {
          "explored": 2,
          "sampled": 2,
          "angelic_found": false,
          "angelic": 0,
          "sample_space_exhausted": true,
          "trials_exhuasted": false,
          "ebits_overflown": false,
          "loc_dd_failed": false,
          "ebits_dd_failed": false,
          "stuck": false,
          "cost": [
            20.0
          ],
          "ratio": [
            1.0
          ],
          "accepted": [
            true
          ]
        }
      },
      {
        "locations": [
          [
            "I",
            [
              101,
              6,
              101,
              6
            ]
          ]
        ],
        "test": "3",
        "time": {
          "mcmc": 0.8758785724639893,
          "dd": 0
        },
        "paths": {
          "explored": 2,
          "sampled": 2,
          "angelic_found": false,
          "angelic": 0,
          "sample_space_exhausted": true,
          "trials_exhuasted": false,
          "ebits_overflown": false,
          "loc_dd_failed": false,
          "ebits_dd_failed": false,
          "stuck": false,
          "cost": [
            10000020.0
          ],
          "ratio": [
            1.0
          ],
          "accepted": [
            true
          ]
        }
      },
      {
        "locations": [
          [
            "I",
            [
              116,
              10,
              116,
              27
            ]
          ]
        ],
        "test": "3",
        "time": {
          "mcmc": 0.9618184566497803,
          "dd": 0
        },
        "paths": {
          "explored": 2,
          "sampled": 2,
          "angelic_found": false,
          "angelic": 0,
          "sample_space_exhausted": true,
          "trials_exhuasted": false,
          "ebits_overflown": false,
          "loc_dd_failed": false,
          "ebits_dd_failed": false,
          "stuck": false,
          "cost": [
            10000020.0
          ],
          "ratio": [
            1.0
          ],
          "accepted": [
            true
          ]
        }
      },
      {
        "locations": [
          [
            "L",
            [
              137,
              14,
              137,
              19
            ]
          ]
        ],
        "test": "3",
        "time": {
          "mcmc": 1.6152632236480713,
          "dd": 0
        },
        "paths": {
          "explored": 3,
          "sampled": 100,
          "angelic_found": false,
          "angelic": 0,
          "sample_space_exhausted": false,
          "trials_exhuasted": true,
          "ebits_overflown": false,
          "loc_dd_failed": false,
          "ebits_dd_failed": false,
          "stuck": false,
          "cost": [
            10000020.0,
            10000020.0,
            10000020.0,
            10000020.0,
            10000020.0,
            10000020.0,
            10000020.0,
            10000020.0,
            10000020.0,
            10000020.0,
            10000020.0,
            10000020.0,
            10000020.0,
            10000020.0,
            10000020.0,
            10000020.0,
            10000020.0,
            10000020.0,
            10000020.0,
            10000020.0,
            10000020.0,
            10000020.0,
            10000020.0,
            10000020.0,
            10000020.0,
            10000020.0,
            10000020.0,
            10000020.0,
            10000020.0,
            10000020.0,
            10000020.0,
            10000020.0,
            10000020.0,
            10000020.0,
            10000020.0,
            10000020.0,
            10000020.0,
            10000020.0,
            10000020.0,
            10000020.0,
            10000020.0,
            10000020.0,
            10000020.0,
            10000020.0,
            10000020.0,
            10000020.0,
            10000020.0,
            10000020.0,
            10000020.0,
            10000020.0,
            10000020.0,
            10000020.0,
            10000020.0,
            10000020.0,
            10000020.0,
            10000020.0,
            10000020.0,
            10000020.0,
            10000020.0,
            10000020.0,
            10000020.0,
            10000020.0,
            10000020.0,
            10000020.0,
            10000020.0,
            10000020.0,
            10000020.0,
            10000020.0,
            10000020.0,
            10000020.0,
            10000020.0,
            10000020.0,
            10000020.0,
            10000020.0,
            10000020.0,
            10000020.0,
            10000020.0,
            10000020.0,
            10000020.0,
            10000020.0,
            10000020.0,
            10000020.0,
            10000020.0,
            10000020.0,
            10000020.0,
            10000020.0,
            10000020.0,
            10000020.0,
            10000020.0,
            10000020.0,
            10000020.0,
            10000020.0,
            10000020.0,
            10000020.0,
            10000020.0,
            10000020.0,
            10000020.0,
            10000020.0,
            10000020.0,
            10000020.0
          ],
          "ratio": [
            1.0,
            0.6592406302004438,
            1.0,
            1.0,
            1.0,
            1.0,
            1.0,
            1.0,
            1.0,
            1.0,
            1.0,
            1.0,
            1.0,
            1.0,
            1.0,
            1.0,
            1.0,
            1.0,
            1.0,
            1.0,
            1.0,
            1.0,
            1.0,
            1.0,
            1.0,
            1.0,
            1.0,
            1.0,
            1.0,
            1.0,
            1.0,
            1.0,
            1.0,
            1.0,
            1.0,
            1.0,
            1.0,
            1.0,
            1.0,
            1.0,
            1.0,
            1.0,
            1.0,
            1.0,
            1.0,
            1.0,
            1.0,
            1.0,
            1.0,
            1.0,
            1.0,
            1.0,
            1.0,
            1.0,
            1.0,
            1.0,
            1.0,
            1.0,
            1.0,
            1.0,
            1.0,
            1.0,
            1.0,
            1.0,
            1.0,
            1.0,
            1.0,
            1.0,
            1.0,
            1.0,
            1.0,
            1.0,
            1.0,
            1.0,
            1.0,
            1.0,
            1.0,
            1.0,
            1.0,
            1.0,
            1.0,
            1.0,
            1.0,
            1.0,
            1.0,
            1.0,
            1.0,
            1.0,
            1.0,
            1.0,
            1.0,
            1.0,
            1.0,
            1.0,
            1.0,
            1.0,
            1.0,
            1.0,
            1.0,
            1.0
          ],
          "accepted": [
            true,
            true,
            true,
            true,
            true,
            true,
            true,
            true,
            true,
            true,
            true,
            true,
            true,
            true,
            true,
            true,
            true,
            true,
            true,
            true,
            true,
            true,
            true,
            true,
            true,
            true,
            true,
            true,
            true,
            true,
            true,
            true,
            true,
            true,
            true,
            true,
            true,
            true,
            true,
            true,
            true,
            true,
            true,
            true,
            true,
            true,
            true,
            true,
            true,
            true,
            true,
            true,
            true,
            true,
            true,
            true,
            true,
            true,
            true,
            true,
            true,
            true,
            true,
            true,
            true,
            true,
            true,
            true,
            true,
            true,
            true,
            true,
            true,
            true,
            true,
            true,
            true,
            true,
            true,
            true,
            true,
            true,
            true,
            true,
            true,
            true,
            true,
            true,
            true,
            true,
            true,
            true,
            true,
            true,
            true,
            true,
            true,
            true,
            true,
            true
          ]
        }
      },
      {
        "locations": [
          [
            "I",
            [
              138,
              31,
              138,
              36
            ]
          ]
        ],
        "test": "3",
        "time": {
          "mcmc": 10.000940799713135,
          "dd": 0
        },
        "paths": {
          "explored": 22,
          "sampled": 21,
          "angelic_found": false,
          "angelic": 0,
          "sample_space_exhausted": false,
          "trials_exhuasted": false,
          "ebits_overflown": false,
          "loc_dd_failed": false,
          "ebits_dd_failed": false,
          "stuck": true,
          "cost": [
            10000020.0,
            10000020.0,
            10000020.0,
            10000020.0,
            10000020.0,
            10000020.0,
            10000020.0,
            10000020.0,
            10000020.0,
            10000020.0,
            10000020.0,
            10000020.0,
            10000020.0,
            10000020.0,
            10000020.0,
            10000020.0,
            10000020.0,
            10000020.0,
            10000020.0,
            10000020.0,
            10000020.0
          ],
          "ratio": [
            1.0,
            1.0,
            1.0,
            1.0,
            1.0,
            1.0,
            1.0,
            1.0,
            1.0,
            1.0,
            1.0,
            1.0,
            1.0,
            1.0,
            1.0,
            1.0,
            1.0,
            1.0,
            1.0,
            1.0
          ],
          "accepted": [
            true,
            true,
            true,
            true,
            true,
            true,
            true,
            true,
            true,
            true,
            true,
            true,
            true,
            true,
            true,
            true,
            true,
            true,
            true,
            true
          ]
        }
      },
      {
        "locations": [
          [
            "I",
            [
              143,
              6,
              143,
              14
            ]
          ]
        ],
        "test": "3",
        "time": {
          "mcmc": 0.8677117824554443,
          "dd": 0
        },
        "paths": {
          "explored": 2,
          "sampled": 2,
          "angelic_found": false,
          "angelic": 0,
          "sample_space_exhausted": true,
          "trials_exhuasted": false,
          "ebits_overflown": false,
          "loc_dd_failed": false,
          "ebits_dd_failed": false,
          "stuck": false,
          "cost": [
            20.0
          ],
          "ratio": [
            1.0
          ],
          "accepted": [
            true
          ]
        }
      },
      {
        "locations": [
          [
            "I",
            [
              153,
              6,
              153,
              25
            ]
          ]
        ],
        "test": "3",
        "time": {
          "mcmc": 0.9250373840332031,
          "dd": 0
        },
        "paths": {
          "explored": 2,
          "sampled": 2,
          "angelic_found": false,
          "angelic": 0,
          "sample_space_exhausted": true,
          "trials_exhuasted": false,
          "ebits_overflown": false,
          "loc_dd_failed": false,
          "ebits_dd_failed": false,
          "stuck": false,
          "cost": [
            10000020.0
          ],
          "ratio": [
            1.0
          ],
          "accepted": [
            true
          ]
        }
      },
      {
        "locations": [
          [
            "L",
            [
              176,
              39,
              176,
              45
            ]
          ]
        ],
        "test": "3",
        "time": {
          "mcmc": 2.691723108291626,
          "dd": 0
        },
        "paths": {
          "explored": 6,
          "sampled": 100,
          "angelic_found": false,
          "angelic": 0,
          "sample_space_exhausted": false,
          "trials_exhuasted": true,
          "ebits_overflown": false,
          "loc_dd_failed": false,
          "ebits_dd_failed": false,
          "stuck": false,
          "cost": [
            20.0,
            20.0,
            20.0,
            20.0,
            20.0,
            20.0,
            20.0,
            20.0,
            20.0,
            20.0,
            20.0,
            20.0,
            20.0,
            20.0,
            20.0,
            20.0,
            20.0,
            20.0,
            20.0,
            20.0,
            20.0,
            20.0,
            20.0,
            20.0,
            20.0,
            20.0,
            20.0,
            20.0,
            20.0,
            20.0,
            20.0,
            20.0,
            20.0,
            20.0,
            20.0,
            20.0,
            20.0,
            20.0,
            20.0,
            20.0,
            20.0,
            20.0,
            20.0,
            20.0,
            20.0,
            20.0,
            20.0,
            20.0,
            20.0,
            20.0,
            20.0,
            20.0,
            20.0,
            20.0,
            20.0,
            20.0,
            20.0,
            20.0,
            20.0,
            20.0,
            20.0,
            20.0,
            20.0,
            20.0,
            20.0,
            20.0,
            20.0,
            20.0,
            20.0,
            20.0,
            20.0,
            20.0,
            20.0,
            20.0,
            20.0,
            20.0,
            20.0,
            20.0,
            20.0,
            20.0,
            20.0,
            20.0,
            20.0,
            20.0,
            20.0,
            20.0,
            20.0,
            20.0,
            20.0,
            20.0,
            20.0,
            20.0,
            20.0,
            20.0,
            20.0,
            20.0,
            20.0,
            20.0,
            20.0,
            20.0
          ],
          "ratio": [
            1.0,
            1.0,
            1.0,
            1.0,
            0.6592406302004438,
            1.0,
            1.0,
            1.0,
            1.0,
            1.0,
            1.0,
            1.0,
            1.0,
            1.0,
            1.0,
            1.0,
            1.0,
            1.0,
            1.0,
            1.0,
            1.0,
            1.0,
            1.0,
            1.0,
            1.0,
            1.0,
            1.0,
            1.0,
            1.0,
            1.0,
            1.0,
            1.0,
            1.0,
            1.0,
            1.0,
            1.0,
            1.0,
            1.0,
            1.0,
            1.0,
            1.0,
            1.0,
            1.0,
            1.0,
            1.0,
            1.0,
            1.0,
            1.0,
            1.0,
            1.0,
            1.0,
            1.0,
            1.0,
            1.0,
            1.0,
            1.0,
            1.0,
            1.0,
            1.0,
            1.0,
            1.0,
            1.0,
            1.0,
            1.0,
            1.0,
            1.0,
            1.0,
            1.0,
            1.0,
            1.0,
            1.0,
            1.0,
            1.0,
            1.0,
            1.0,
            1.0,
            1.0,
            1.0,
            1.0,
            1.0,
            1.0,
            1.0,
            1.0,
            1.0,
            1.0,
            1.0,
            1.0,
            1.0,
            1.0,
            1.0,
            1.0,
            1.0,
            1.0,
            1.0,
            1.0,
            1.0,
            1.0,
            1.0,
            1.0,
            1.0
          ],
          "accepted": [
            true,
            true,
            true,
            true,
            true,
            true,
            true,
            true,
            true,
            true,
            true,
            true,
            true,
            true,
            true,
            true,
            true,
            true,
            true,
            true,
            true,
            true,
            true,
            true,
            true,
            true,
            true,
            true,
            true,
            true,
            true,
            true,
            true,
            true,
            true,
            true,
            true,
            true,
            true,
            true,
            true,
            true,
            true,
            true,
            true,
            true,
            true,
            true,
            true,
            true,
            true,
            true,
            true,
            true,
            true,
            true,
            true,
            true,
            true,
            true,
            true,
            true,
            true,
            true,
            true,
            true,
            true,
            true,
            true,
            true,
            true,
            true,
            true,
            true,
            true,
            true,
            true,
            true,
            true,
            true,
            true,
            true,
            true,
            true,
            true,
            true,
            true,
            true,
            true,
            true,
            true,
            true,
            true,
            true,
            true,
            true,
            true,
            true,
            true,
            true
          ]
        }
      },
      {
        "locations": [
          [
            "I",
            [
              184,
              21,
              184,
              39
            ]
          ]
        ],
        "test": "3",
        "time": {
          "mcmc": 9.767146348953247,
          "dd": 0
        },
        "paths": {
          "explored": 22,
          "sampled": 21,
          "angelic_found": false,
          "angelic": 0,
          "sample_space_exhausted": false,
          "trials_exhuasted": false,
          "ebits_overflown": false,
          "loc_dd_failed": false,
          "ebits_dd_failed": false,
          "stuck": true,
          "cost": [
            10000020.0,
            10000020.0,
            10000020.0,
            10000020.0,
            10000020.0,
            10000020.0,
            10000020.0,
            10000020.0,
            10000020.0,
            10000020.0,
            10000020.0,
            10000020.0,
            10000020.0,
            10000020.0,
            10000020.0,
            10000020.0,
            10000020.0,
            10000020.0,
            10000020.0,
            10000020.0,
            10000020.0
          ],
          "ratio": [
            1.0,
            1.0,
            1.0,
            1.0,
            1.0,
            1.0,
            1.0,
            1.0,
            1.0,
            1.0,
            1.0,
            1.0,
            1.0,
            1.0,
            1.0,
            1.0,
            1.0,
            1.0,
            1.0,
            1.0
          ],
          "accepted": [
            true,
            true,
            true,
            true,
            true,
            true,
            true,
            true,
            true,
            true,
            true,
            true,
            true,
            true,
            true,
            true,
            true,
            true,
            true,
            true
          ]
        }
      },
      {
        "locations": [
          [
            "L",
            [
              188,
              34,
              188,
              43
            ]
          ]
        ],
        "test": "3",
        "time": {
          "mcmc": 27.113378047943115,
          "dd": 0
        },
        "paths": {
          "explored": 58,
          "sampled": 61,
          "angelic_found": false,
          "angelic": 0,
          "sample_space_exhausted": false,
          "trials_exhuasted": false,
          "ebits_overflown": true,
          "loc_dd_failed": false,
          "ebits_dd_failed": false,
          "stuck": true,
          "cost": [
            7.0,
            7.0,
            7.0,
            7.0,
            7.0,
            7.0,
            10000020.0,
            7.0,
            10000020.0,
            7.0,
            7.0,
            6.0,
            6.0,
            7.0,
            6.0,
            2.0,
            10000020.0,
            7.0,
            2.0,
            2.0,
            2.0,
            7.0,
            2.0,
            7.0,
            2.0,
            6.0,
            6.0,
            7.0,
            6.0,
            6.0,
            6.0,
            7.0,
            6.0,
            2.0,
            2.0,
            7.0,
            2.0,
            6.0,
            6.0,
            2.0,
            2.0,
            6.0,
            6.0,
            2.0,
            6.0,
            2.0,
            2.0,
            7.0,
            6.0,
            7.0,
            7.0,
            2.0,
            7.0,
            7.0,
            6.0,
            2.0,
            2.0,
            2.0,
            2.0
          ],
          "ratio": [
            1.0,
            1.0,
            1.0,
            1.0,
            1.0,
            1.0,
            0.0,
            0.9998984321353007,
            0.0,
            1.0,
            1.0,
            1.0,
            1.0,
            0.44932896411722156,
            1.0,
            1.0,
            0.0,
            0.01831563888873418,
            0.9999866481980227,
            0.9999867851176122,
            1.0,
            0.01831563888873418,
            1.0,
            0.01831563888873418,
            1.0,
            0.04076220397836621,
            0.04076220397836621,
            0.01831563888873418,
            0.04076220397836621,
            0.04076220397836621,
            0.04076220397836621,
            0.01831563888873418,
            0.04076220397836621,
            1.0,
            0.9999867851176122,
            0.01831563888873418,
            1.0,
            0.04076167621843393,
            0.04076220397836621,
            0.9999870527135244,
            1.0,
            0.04076220397836621,
            0.04076220397836621,
            1.0,
            0.04076220397836621,
            1.0,
            0.9999866481980227,
            0.01831588343878289,
            0.04076220397836621,
            0.01831563888873418,
            0.01831563888873418,
            1.0,
            0.01831563888873418,
            0.01831563888873418,
            0.04076220397836621,
            1.0,
            0.9999870527135244,
            0.9999871834738384
          ],
          "accepted": [
            true,
            true,
            true,
            true,
            true,
            true,
            false,
            true,
            false,
            true,
            true,
            true,
            true,
            false,
            true,
            true,
            false,
            false,
            true,
            true,
            true,
            false,
            true,
            false,
            true,
            false,
            false,
            false,
            false,
            false,
            false,
            false,
            true,
            true,
            true,
            false,
            true,
            false,
            false,
            true,
            true,
            false,
            false,
            true,
            false,
            true,
            true,
            false,
            false,
            false,
            false,
            true,
            false,
            false,
            true,
            true,
            true,
            true
          ]
        }
      },
      {
        "locations": [
          [
            "I",
            [
              191,
              25,
              191,
              26
            ]
          ]
        ],
        "test": "3",
        "time": {
          "mcmc": 9.594715356826782,
          "dd": 0
        },
        "paths": {
          "explored": 22,
          "sampled": 22,
          "angelic_found": false,
          "angelic": 0,
          "sample_space_exhausted": false,
          "trials_exhuasted": false,
          "ebits_overflown": false,
          "loc_dd_failed": false,
          "ebits_dd_failed": false,
          "stuck": true,
          "cost": [
            10000020.0,
            10000020.0,
            10000020.0,
            10000020.0,
            10000020.0,
            10000020.0,
            10000020.0,
            10000020.0,
            10000020.0,
            10000020.0,
            10000020.0,
            10000020.0,
            10000020.0,
            10000020.0,
            10000020.0,
            10000020.0,
            10000020.0,
            10000020.0,
            10000020.0,
            10000020.0,
            10000020.0,
            10000020.0
          ],
          "ratio": [
            1.0,
            0.9973250127430101,
            1.0,
            1.0,
            0.9999884838047957,
            1.0,
            1.0,
            1.0,
            0.9973250127430101,
            1.0,
            1.0,
            1.0,
            1.0,
            1.0,
            1.0,
            1.0,
            0.9999996299996985,
            1.0,
            0.9932983288814592,
            1.0,
            0.999999530892498
          ],
          "accepted": [
            true,
            true,
            true,
            true,
            true,
            true,
            true,
            true,
            true,
            true,
            true,
            true,
            true,
            true,
            true,
            true,
            true,
            true,
            true,
            true,
            true
          ]
        }
      },
      {
        "locations": [
          [
            "I",
            [
              213,
              8,
              213,
              20
            ]
          ]
        ],
        "test": "3",
        "time": {
          "mcmc": 0.8766739368438721,
          "dd": 0
        },
        "paths": {
          "explored": 2,
          "sampled": 2,
          "angelic_found": false,
          "angelic": 0,
          "sample_space_exhausted": true,
          "trials_exhuasted": false,
          "ebits_overflown": false,
          "loc_dd_failed": false,
          "ebits_dd_failed": false,
          "stuck": false,
          "cost": [
            10000020.0
          ],
          "ratio": [
            0.6592406302004438
          ],
          "accepted": [
            false
          ]
        }
      },
      {
        "locations": [
          [
            "I",
            [
              231,
              8,
              231,
              20
            ]
          ]
        ],
        "test": "3",
        "time": {
          "mcmc": 1.086944341659546,
          "dd": 0
        },
        "paths": {
          "explored": 2,
          "sampled": 100,
          "angelic_found": false,
          "angelic": 0,
          "sample_space_exhausted": false,
          "trials_exhuasted": true,
          "ebits_overflown": false,
          "loc_dd_failed": false,
          "ebits_dd_failed": false,
          "stuck": false,
          "cost": [
            10000020.0,
            10000020.0,
            10000020.0,
            10000020.0,
            10000020.0,
            10000020.0,
            10000020.0,
            10000020.0,
            10000020.0,
            10000020.0,
            10000020.0,
            10000020.0,
            10000020.0,
            10000020.0,
            10000020.0,
            10000020.0,
            10000020.0,
            10000020.0,
            10000020.0,
            10000020.0,
            10000020.0,
            10000020.0,
            10000020.0,
            10000020.0,
            10000020.0,
            10000020.0,
            10000020.0,
            10000020.0,
            10000020.0,
            10000020.0,
            10000020.0,
            10000020.0,
            10000020.0,
            10000020.0,
            10000020.0,
            10000020.0,
            10000020.0,
            10000020.0,
            10000020.0,
            10000020.0,
            10000020.0,
            10000020.0,
            10000020.0,
            10000020.0,
            10000020.0,
            10000020.0,
            10000020.0,
            10000020.0,
            10000020.0,
            10000020.0,
            10000020.0,
            10000020.0,
            10000020.0,
            10000020.0,
            10000020.0,
            10000020.0,
            10000020.0,
            10000020.0,
            10000020.0,
            10000020.0,
            10000020.0,
            10000020.0,
            10000020.0,
            10000020.0,
            10000020.0,
            10000020.0,
            10000020.0,
            10000020.0,
            10000020.0,
            10000020.0,
            10000020.0,
            10000020.0,
            10000020.0,
            10000020.0,
            10000020.0,
            10000020.0,
            10000020.0,
            10000020.0,
            10000020.0,
            10000020.0,
            10000020.0,
            10000020.0,
            10000020.0,
            10000020.0,
            10000020.0,
            10000020.0,
            10000020.0,
            10000020.0,
            10000020.0,
            10000020.0,
            10000020.0,
            10000020.0,
            10000020.0,
            10000020.0,
            10000020.0,
            10000020.0,
            10000020.0,
            10000020.0,
            10000020.0,
            10000020.0
          ],
          "ratio": [
            1.0,
            0.6592406302004438,
            1.0,
            1.0,
            1.0,
            1.0,
            1.0,
            1.0,
            1.0,
            1.0,
            1.0,
            1.0,
            1.0,
            1.0,
            1.0,
            1.0,
            1.0,
            1.0,
            1.0,
            1.0,
            1.0,
            1.0,
            1.0,
            1.0,
            1.0,
            1.0,
            1.0,
            1.0,
            1.0,
            1.0,
            1.0,
            1.0,
            1.0,
            1.0,
            1.0,
            1.0,
            1.0,
            1.0,
            1.0,
            1.0,
            1.0,
            1.0,
            1.0,
            1.0,
            1.0,
            1.0,
            1.0,
            1.0,
            1.0,
            1.0,
            1.0,
            1.0,
            1.0,
            1.0,
            1.0,
            1.0,
            1.0,
            1.0,
            1.0,
            1.0,
            1.0,
            1.0,
            1.0,
            1.0,
            1.0,
            1.0,
            1.0,
            1.0,
            1.0,
            1.0,
            1.0,
            1.0,
            1.0,
            1.0,
            1.0,
            1.0,
            1.0,
            1.0,
            1.0,
            1.0,
            1.0,
            1.0,
            1.0,
            1.0,
            1.0,
            1.0,
            1.0,
            1.0,
            1.0,
            1.0,
            1.0,
            1.0,
            1.0,
            1.0,
            1.0,
            1.0,
            1.0,
            1.0,
            1.0,
            1.0
          ],
          "accepted": [
            true,
            true,
            true,
            true,
            true,
            true,
            true,
            true,
            true,
            true,
            true,
            true,
            true,
            true,
            true,
            true,
            true,
            true,
            true,
            true,
            true,
            true,
            true,
            true,
            true,
            true,
            true,
            true,
            true,
            true,
            true,
            true,
            true,
            true,
            true,
            true,
            true,
            true,
            true,
            true,
            true,
            true,
            true,
            true,
            true,
            true,
            true,
            true,
            true,
            true,
            true,
            true,
            true,
            true,
            true,
            true,
            true,
            true,
            true,
            true,
            true,
            true,
            true,
            true,
            true,
            true,
            true,
            true,
            true,
            true,
            true,
            true,
            true,
            true,
            true,
            true,
            true,
            true,
            true,
            true,
            true,
            true,
            true,
            true,
            true,
            true,
            true,
            true,
            true,
            true,
            true,
            true,
            true,
            true,
            true,
            true,
            true,
            true,
            true,
            true
          ]
        }
      },
      {
        "locations": [
          [
            "I",
            [
              344,
              21,
              344,
              39
            ]
          ]
        ],
        "test": "3",
        "time": {
          "mcmc": 9.30190634727478,
          "dd": 0
        },
        "paths": {
          "explored": 22,
          "sampled": 22,
          "angelic_found": false,
          "angelic": 0,
          "sample_space_exhausted": false,
          "trials_exhuasted": false,
          "ebits_overflown": false,
          "loc_dd_failed": false,
          "ebits_dd_failed": false,
          "stuck": true,
          "cost": [
            10000020.0,
            10000020.0,
            10000020.0,
            10000020.0,
            10000020.0,
            10000020.0,
            10000020.0,
            10000020.0,
            10000020.0,
            10000020.0,
            10000020.0,
            10000020.0,
            10000020.0,
            10000020.0,
            10000020.0,
            10000020.0,
            10000020.0,
            10000020.0,
            10000020.0,
            10000020.0,
            10000020.0,
            10000020.0
          ],
          "ratio": [
            1.0,
            0.9983931053055055,
            0.9999998508529012,
            0.9999999823847652,
            1.0,
            1.0,
            1.0,
            0.9999999988051999,
            1.0,
            1.0,
            1.0,
            1.0,
            1.0,
            1.0,
            0.9988931568628883,
            1.0,
            0.9991029666777216,
            1.0,
            1.0,
            1.0,
            1.0
          ],
          "accepted": [
            true,
            true,
            true,
            true,
            true,
            true,
            true,
            true,
            true,
            true,
            true,
            true,
            true,
            true,
            true,
            true,
            true,
            true,
            true,
            true,
            true
          ]
        }
      },
      {
        "locations": [
          [
            "I",
            [
              444,
              7,
              444,
              12
            ]
          ]
        ],
        "test": "3",
        "time": {
          "mcmc": 3.744858741760254,
          "dd": 0
        },
        "paths": {
          "explored": 8,
          "sampled": 100,
          "angelic_found": false,
          "angelic": 0,
          "sample_space_exhausted": false,
          "trials_exhuasted": true,
          "ebits_overflown": false,
          "loc_dd_failed": false,
          "ebits_dd_failed": false,
          "stuck": false,
          "cost": [
            20.0,
            10000020.0,
            10000020.0,
            20.0,
            10000020.0,
            20.0,
            20.0,
            10000020.0,
            20.0,
            20.0,
            20.0,
            20.0,
            20.0,
            10000020.0,
            20.0,
            10000020.0,
            10000020.0,
            10000020.0,
            10000020.0,
            10000020.0,
            20.0,
            20.0,
            10000020.0,
            20.0,
            20.0,
            20.0,
            20.0,
            10000020.0,
            20.0,
            20.0,
            10000020.0,
            10000020.0,
            20.0,
            10000020.0,
            10000020.0,
            10000020.0,
            20.0,
            10000020.0,
            10000020.0,
            20.0,
            20.0,
            10000020.0,
            20.0,
            10000020.0,
            20.0,
            10000020.0,
            20.0,
            20.0,
            20.0,
            10000020.0,
            20.0,
            20.0,
            10000020.0,
            20.0,
            20.0,
            20.0,
            20.0,
            20.0,
            10000020.0,
            20.0,
            10000020.0,
            20.0,
            20.0,
            20.0,
            20.0,
            20.0,
            20.0,
            20.0,
            20.0,
            20.0,
            20.0,
            10000020.0,
            20.0,
            20.0,
            20.0,
            20.0,
            20.0,
            10000020.0,
            20.0,
            10000020.0,
            10000020.0,
            10000020.0,
            20.0,
            20.0,
            10000020.0,
            20.0,
            20.0,
            20.0,
            20.0,
            10000020.0,
            20.0,
            20.0,
            10000020.0,
            20.0,
            20.0,
            10000020.0,
            10000020.0,
            10000020.0,
            20.0,
            10000020.0
          ],
          "ratio": [
            1.0,
            0.0,
            0.0,
            1.0,
            0.0,
            1.0,
            1.0,
            0.0,
            1.0,
            1.0,
            1.0,
            1.0,
            1.0,
            0.0,
            1.0,
            0.0,
            0.0,
            0.0,
            0.0,
            0.0,
            1.0,
            1.0,
            0.0,
            1.0,
            1.0,
            1.0,
            1.0,
            0.0,
            1.0,
            1.0,
            0.0,
            0.0,
            1.0,
            0.0,
            0.0,
            0.0,
            1.0,
            0.0,
            0.0,
            1.0,
            1.0,
            0.0,
            1.0,
            0.0,
            1.0,
            0.0,
            1.0,
            1.0,
            1.0,
            0.0,
            1.0,
            1.0,
            0.0,
            1.0,
            1.0,
            1.0,
            1.0,
            1.0,
            0.0,
            1.0,
            0.0,
            1.0,
            1.0,
            1.0,
            1.0,
            1.0,
            1.0,
            1.0,
            1.0,
            1.0,
            1.0,
            0.0,
            1.0,
            1.0,
            1.0,
            1.0,
            1.0,
            0.0,
            1.0,
            0.0,
            0.0,
            0.0,
            1.0,
            1.0,
            0.0,
            1.0,
            1.0,
            1.0,
            1.0,
            0.0,
            1.0,
            1.0,
            0.0,
            1.0,
            1.0,
            0.0,
            0.0,
            0.0,
            1.0,
            0.0
          ],
          "accepted": [
            true,
            false,
            false,
            true,
            false,
            true,
            true,
            true,
            true,
            true,
            true,
            true,
            true,
            false,
            true,
            false,
            false,
            false,
            false,
            false,
            true,
            true,
            false,
            true,
            true,
            true,
            true,
            false,
            true,
            true,
            false,
            false,
            true,
            false,
            false,
            false,
            true,
            false,
            false,
            true,
            true,
            false,
            true,
            false,
            true,
            false,
            true,
            true,
            true,
            false,
            true,
            true,
            false,
            true,
            true,
            true,
            true,
            true,
            false,
            true,
            false,
            true,
            true,
            true,
            true,
            true,
            true,
            true,
            true,
            true,
            true,
            false,
            true,
            true,
            true,
            true,
            true,
            false,
            true,
            false,
            false,
            false,
            true,
            true,
            false,
            true,
            true,
            true,
            true,
            false,
            true,
            true,
            false,
            true,
            true,
            false,
            false,
            false,
            true,
            false
          ]
        }
      },
      {
        "locations": [
          [
            "I",
            [
              456,
              8,
              456,
              14
            ]
          ]
        ],
        "test": "3",
        "time": {
          "mcmc": 1.983180284500122,
          "dd": 0
        },
        "paths": {
          "explored": 4,
          "sampled": 100,
          "angelic_found": false,
          "angelic": 0,
          "sample_space_exhausted": false,
          "trials_exhuasted": true,
          "ebits_overflown": false,
          "loc_dd_failed": false,
          "ebits_dd_failed": false,
          "stuck": false,
          "cost": [
            10000020.0,
            10000020.0,
            10000020.0,
            10000020.0,
            10000020.0,
            10000020.0,
            10000020.0,
            10000020.0,
            10000020.0,
            10000020.0,
            10000020.0,
            10000020.0,
            10000020.0,
            10000020.0,
            10000020.0,
            10000020.0,
            10000020.0,
            10000020.0,
            10000020.0,
            10000020.0,
            10000020.0,
            10000020.0,
            10000020.0,
            10000020.0,
            10000020.0,
            10000020.0,
            10000020.0,
            10000020.0,
            10000020.0,
            10000020.0,
            10000020.0,
            10000020.0,
            10000020.0,
            10000020.0,
            10000020.0,
            10000020.0,
            10000020.0,
            10000020.0,
            10000020.0,
            10000020.0,
            10000020.0,
            10000020.0,
            10000020.0,
            10000020.0,
            10000020.0,
            10000020.0,
            10000020.0,
            10000020.0,
            10000020.0,
            10000020.0,
            10000020.0,
            10000020.0,
            10000020.0,
            10000020.0,
            10000020.0,
            10000020.0,
            10000020.0,
            10000020.0,
            10000020.0,
            10000020.0,
            10000020.0,
            10000020.0,
            10000020.0,
            10000020.0,
            10000020.0,
            10000020.0,
            10000020.0,
            10000020.0,
            10000020.0,
            10000020.0,
            10000020.0,
            10000020.0,
            10000020.0,
            10000020.0,
            10000020.0,
            10000020.0,
            10000020.0,
            10000020.0,
            10000020.0,
            10000020.0,
            10000020.0,
            10000020.0,
            10000020.0,
            10000020.0,
            10000020.0,
            10000020.0,
            10000020.0,
            10000020.0,
            10000020.0,
            10000020.0,
            10000020.0,
            10000020.0,
            10000020.0,
            10000020.0,
            10000020.0,
            10000020.0,
            10000020.0,
            10000020.0,
            10000020.0,
            10000020.0
          ],
          "ratio": [
            1.0,
            1.0,
            1.0,
            0.6592406302004438,
            1.0,
            1.0,
            1.0,
            1.0,
            1.0,
            1.0,
            1.0,
            1.0,
            1.0,
            1.0,
            1.0,
            1.0,
            1.0,
            1.0,
            1.0,
            1.0,
            1.0,
            1.0,
            1.0,
            1.0,
            1.0,
            1.0,
            1.0,
            1.0,
            1.0,
            1.0,
            1.0,
            1.0,
            1.0,
            1.0,
            1.0,
            1.0,
            1.0,
            1.0,
            1.0,
            1.0,
            1.0,
            1.0,
            1.0,
            1.0,
            1.0,
            1.0,
            1.0,
            1.0,
            1.0,
            1.0,
            1.0,
            1.0,
            1.0,
            1.0,
            1.0,
            1.0,
            1.0,
            1.0,
            1.0,
            1.0,
            1.0,
            1.0,
            1.0,
            1.0,
            1.0,
            1.0,
            1.0,
            1.0,
            1.0,
            1.0,
            1.0,
            1.0,
            1.0,
            1.0,
            1.0,
            1.0,
            1.0,
            1.0,
            1.0,
            1.0,
            1.0,
            1.0,
            1.0,
            1.0,
            1.0,
            1.0,
            1.0,
            1.0,
            1.0,
            1.0,
            1.0,
            1.0,
            1.0,
            1.0,
            1.0,
            1.0,
            1.0,
            1.0,
            1.0,
            1.0
          ],
          "accepted": [
            true,
            true,
            true,
            true,
            true,
            true,
            true,
            true,
            true,
            true,
            true,
            true,
            true,
            true,
            true,
            true,
            true,
            true,
            true,
            true,
            true,
            true,
            true,
            true,
            true,
            true,
            true,
            true,
            true,
            true,
            true,
            true,
            true,
            true,
            true,
            true,
            true,
            true,
            true,
            true,
            true,
            true,
            true,
            true,
            true,
            true,
            true,
            true,
            true,
            true,
            true,
            true,
            true,
            true,
            true,
            true,
            true,
            true,
            true,
            true,
            true,
            true,
            true,
            true,
            true,
            true,
            true,
            true,
            true,
            true,
            true,
            true,
            true,
            true,
            true,
            true,
            true,
            true,
            true,
            true,
            true,
            true,
            true,
            true,
            true,
            true,
            true,
            true,
            true,
            true,
            true,
            true,
            true,
            true,
            true,
            true,
            true,
            true,
            true,
            true
          ]
        }
      },
      {
        "locations": [
          [
            "I",
            [
              647,
              6,
              647,
              10
            ]
          ]
        ],
        "test": "3",
        "time": {
          "mcmc": 3.517037868499756,
          "dd": 0
        },
        "paths": {
          "explored": 8,
          "sampled": 23,
          "angelic_found": false,
          "angelic": 0,
          "sample_space_exhausted": true,
          "trials_exhuasted": false,
          "ebits_overflown": false,
          "loc_dd_failed": false,
          "ebits_dd_failed": false,
          "stuck": false,
          "cost": [
            10000020.0,
            10000020.0,
            10000020.0,
            10000020.0,
            10000020.0,
            10000020.0,
            10000020.0,
            10000020.0,
            10000020.0,
            10000020.0,
            10000020.0,
            10000020.0,
            10000020.0,
            10000020.0,
            10000020.0,
            10000020.0,
            10000020.0,
            10000020.0,
            10000020.0,
            10000020.0,
            10000020.0,
            10000020.0
          ],
          "ratio": [
            1.0,
            1.0,
            1.0,
            1.0,
            1.0,
            1.0,
            1.0,
            1.0,
            1.0,
            1.0,
            1.0,
            1.0,
            1.0,
            1.0,
            1.0,
            1.0,
            1.0,
            1.0,
            1.0,
            1.0,
            1.0,
            1.0
          ],
          "accepted": [
            true,
            true,
            true,
            true,
            true,
            true,
            true,
            true,
            true,
            true,
            true,
            true,
            true,
            true,
            true,
            true,
            true,
            true,
            true,
            true,
            true,
            true
          ]
        }
      },
      {
        "locations": [
          [
            "L",
            [
              693,
              14,
              693,
              18
            ]
          ]
        ],
        "test": "3",
        "time": {
          "mcmc": 9.55418872833252,
          "dd": 0
        },
        "paths": {
          "explored": 22,
          "sampled": 97,
          "angelic_found": false,
          "angelic": 0,
          "sample_space_exhausted": false,
          "trials_exhuasted": false,
          "ebits_overflown": false,
          "loc_dd_failed": false,
          "ebits_dd_failed": false,
          "stuck": true,
          "cost": [
            10000020.0,
            10000020.0,
            10000020.0,
            10000020.0,
            10000020.0,
            10000020.0,
            10000020.0,
            10000020.0,
            10000020.0,
            10000020.0,
            10000020.0,
            10000020.0,
            10000020.0,
            10000020.0,
            10000020.0,
            10000020.0,
            10000020.0,
            10000020.0,
            10000020.0,
            10000020.0,
            10000020.0,
            10000020.0,
            10000020.0,
            10000020.0,
            10000020.0,
            10000020.0,
            10000020.0,
            10000020.0,
            10000020.0,
            10000020.0,
            10000020.0,
            10000020.0,
            10000020.0,
            10000020.0,
            10000020.0,
            10000020.0,
            10000020.0,
            10000020.0,
            10000020.0,
            10000020.0,
            10000020.0,
            10000020.0,
            10000020.0,
            10000020.0,
            10000020.0,
            10000020.0,
            10000020.0,
            10000020.0,
            10000020.0,
            10000020.0,
            10000020.0,
            10000020.0,
            10000020.0,
            10000020.0,
            10000020.0,
            10000020.0,
            10000020.0,
            10000020.0,
            10000020.0,
            10000020.0,
            10000020.0,
            10000020.0,
            10000020.0,
            10000020.0,
            10000020.0,
            10000020.0,
            10000020.0,
            10000020.0,
            10000020.0,
            10000020.0,
            10000020.0,
            10000020.0,
            10000020.0,
            10000020.0,
            10000020.0,
            10000020.0,
            10000020.0,
            10000020.0,
            10000020.0,
            10000020.0,
            10000020.0,
            10000020.0,
            10000020.0,
            10000020.0,
            10000020.0,
            10000020.0,
            10000020.0,
            10000020.0,
            10000020.0,
            10000020.0,
            10000020.0,
            10000020.0,
            10000020.0,
            10000020.0,
            10000020.0,
            10000020.0,
            10000020.0
          ],
          "ratio": [
            1.0,
            1.0,
            0.9433354498734922,
            1.0,
            1.0,
            1.0,
            1.0,
            1.0,
            0.9799653204514579,
            1.0,
            0.9977745887510434,
            1.0,
            1.0,
            1.0,
            0.9672161004820059,
            1.0,
            1.0,
            1.0,
            1.0,
            0.9787993892143565,
            1.0,
            0.9852292218149133,
            1.0,
            1.0,
            1.0,
            0.9991273650944698,
            1.0,
            1.0,
            1.0,
            1.0,
            1.0,
            1.0,
            0.9651621277986078,
            1.0,
            1.0,
            1.0,
            1.0,
            1.0,
            1.0,
            1.0,
            1.0,
            0.9998441164594919,
            1.0,
            1.0,
            1.0,
            1.0,
            1.0,
            1.0,
            1.0,
            0.9787993892143565,
            1.0,
            1.0,
            1.0,
            1.0,
            1.0,
            1.0,
            1.0,
            1.0,
            1.0,
            1.0,
            0.9994615962385156,
            1.0,
            1.0,
            1.0,
            1.0,
            1.0,
            1.0,
            1.0,
            1.0,
            1.0,
            1.0,
            1.0,
            1.0,
            1.0,
            1.0,
            1.0,
            1.0,
            1.0,
            1.0,
            1.0,
            1.0,
            1.0,
            1.0,
            1.0,
            1.0,
            1.0,
            1.0,
            1.0,
            1.0,
            1.0,
            1.0,
            1.0,
            1.0,
            1.0,
            1.0,
            1.0
          ],
          "accepted": [
            true,
            true,
            true,
            true,
            true,
            true,
            true,
            true,
            true,
            true,
            true,
            true,
            true,
            true,
            true,
            true,
            true,
            true,
            true,
            true,
            true,
            true,
            true,
            true,
            true,
            true,
            true,
            true,
            true,
            true,
            true,
            true,
            true,
            true,
            true,
            true,
            true,
            true,
            true,
            true,
            true,
            true,
            true,
            true,
            true,
            true,
            true,
            true,
            true,
            true,
            true,
            true,
            true,
            true,
            true,
            true,
            true,
            true,
            true,
            true,
            true,
            true,
            true,
            true,
            true,
            true,
            true,
            true,
            true,
            true,
            true,
            true,
            true,
            true,
            true,
            true,
            true,
            true,
            true,
            true,
            true,
            true,
            true,
            true,
            true,
            true,
            true,
            true,
            true,
            true,
            true,
            true,
            true,
            true,
            true,
            true
          ]
        }
      },
      {
        "locations": [
          [
            "I",
            [
              700,
              6,
              700,
              11
            ]
          ]
        ],
        "test": "3",
        "time": {
          "mcmc": 1.8858766555786133,
          "dd": 0
        },
        "paths": {
          "explored": 4,
          "sampled": 100,
          "angelic_found": false,
          "angelic": 0,
          "sample_space_exhausted": false,
          "trials_exhuasted": true,
          "ebits_overflown": false,
          "loc_dd_failed": false,
          "ebits_dd_failed": false,
          "stuck": false,
          "cost": [
            10000020.0,
            10000020.0,
            10000020.0,
            10000020.0,
            10000020.0,
            10000020.0,
            10000020.0,
            10000020.0,
            10000020.0,
            10000020.0,
            10000020.0,
            10000020.0,
            10000020.0,
            10000020.0,
            10000020.0,
            10000020.0,
            10000020.0,
            10000020.0,
            10000020.0,
            10000020.0,
            10000020.0,
            10000020.0,
            10000020.0,
            10000020.0,
            10000020.0,
            10000020.0,
            10000020.0,
            10000020.0,
            10000020.0,
            10000020.0,
            10000020.0,
            10000020.0,
            10000020.0,
            10000020.0,
            10000020.0,
            10000020.0,
            10000020.0,
            10000020.0,
            10000020.0,
            10000020.0,
            10000020.0,
            10000020.0,
            10000020.0,
            10000020.0,
            10000020.0,
            10000020.0,
            10000020.0,
            10000020.0,
            10000020.0,
            10000020.0,
            10000020.0,
            10000020.0,
            10000020.0,
            10000020.0,
            10000020.0,
            10000020.0,
            10000020.0,
            10000020.0,
            10000020.0,
            10000020.0,
            10000020.0,
            10000020.0,
            10000020.0,
            10000020.0,
            10000020.0,
            10000020.0,
            10000020.0,
            10000020.0,
            10000020.0,
            10000020.0,
            10000020.0,
            10000020.0,
            10000020.0,
            10000020.0,
            10000020.0,
            10000020.0,
            10000020.0,
            10000020.0,
            10000020.0,
            10000020.0,
            10000020.0,
            10000020.0,
            10000020.0,
            10000020.0,
            10000020.0,
            10000020.0,
            10000020.0,
            10000020.0,
            10000020.0,
            10000020.0,
            10000020.0,
            10000020.0,
            10000020.0,
            10000020.0,
            10000020.0,
            10000020.0,
            10000020.0,
            10000020.0,
            10000020.0,
            10000020.0
          ],
          "ratio": [
            1.0,
            1.0,
            0.5981648531319816,
            1.0,
            1.0,
            1.0,
            1.0,
            1.0,
            1.0,
            1.0,
            1.0,
            1.0,
            1.0,
            1.0,
            1.0,
            1.0,
            1.0,
            1.0,
            1.0,
            1.0,
            1.0,
            1.0,
            1.0,
            1.0,
            1.0,
            1.0,
            1.0,
            1.0,
            1.0,
            1.0,
            1.0,
            1.0,
            1.0,
            1.0,
            1.0,
            1.0,
            1.0,
            1.0,
            1.0,
            1.0,
            1.0,
            1.0,
            1.0,
            1.0,
            1.0,
            1.0,
            1.0,
            1.0,
            1.0,
            1.0,
            1.0,
            1.0,
            1.0,
            1.0,
            1.0,
            1.0,
            1.0,
            1.0,
            1.0,
            1.0,
            1.0,
            1.0,
            1.0,
            1.0,
            1.0,
            1.0,
            1.0,
            1.0,
            1.0,
            1.0,
            1.0,
            1.0,
            1.0,
            1.0,
            1.0,
            1.0,
            1.0,
            1.0,
            1.0,
            1.0,
            1.0,
            1.0,
            1.0,
            1.0,
            1.0,
            1.0,
            1.0,
            1.0,
            1.0,
            1.0,
            1.0,
            1.0,
            1.0,
            1.0,
            1.0,
            1.0,
            1.0,
            1.0,
            1.0,
            1.0
          ],
          "accepted": [
            true,
            true,
            true,
            true,
            true,
            true,
            true,
            true,
            true,
            true,
            true,
            true,
            true,
            true,
            true,
            true,
            true,
            true,
            true,
            true,
            true,
            true,
            true,
            true,
            true,
            true,
            true,
            true,
            true,
            true,
            true,
            true,
            true,
            true,
            true,
            true,
            true,
            true,
            true,
            true,
            true,
            true,
            true,
            true,
            true,
            true,
            true,
            true,
            true,
            true,
            true,
            true,
            true,
            true,
            true,
            true,
            true,
            true,
            true,
            true,
            true,
            true,
            true,
            true,
            true,
            true,
            true,
            true,
            true,
            true,
            true,
            true,
            true,
            true,
            true,
            true,
            true,
            true,
            true,
            true,
            true,
            true,
            true,
            true,
            true,
            true,
            true,
            true,
            true,
            true,
            true,
            true,
            true,
            true,
            true,
            true,
            true,
            true,
            true,
            true
          ]
        }
      },
      {
        "locations": [
          [
            "I",
            [
              799,
              6,
              799,
              25
            ]
          ]
        ],
        "test": "3",
        "time": {
          "mcmc": 11.781524181365967,
          "dd": 0
        },
        "paths": {
          "explored": 26,
          "sampled": 39,
          "angelic_found": false,
          "angelic": 0,
          "sample_space_exhausted": false,
          "trials_exhuasted": false,
          "ebits_overflown": false,
          "loc_dd_failed": false,
          "ebits_dd_failed": false,
          "stuck": true,
          "cost": [
            10000020.0,
            10000020.0,
            10000020.0,
            10000020.0,
            10000020.0,
            10000020.0,
            10000020.0,
            10000020.0,
            10000020.0,
            10000020.0,
            10000020.0,
            10000020.0,
            10000020.0,
            20.0,
            10000020.0,
            20.0,
            20.0,
            10000020.0,
            20.0,
            10000020.0,
            20.0,
            20.0,
            20.0,
            10000020.0,
            10000020.0,
            20.0,
            20.0,
            10000020.0,
            20.0,
            20.0,
            20.0,
            20.0,
            10000020.0,
            20.0,
            20.0,
            20.0,
            20.0,
            20.0,
            20.0
          ],
          "ratio": [
            1.0,
            1.0,
            1.0,
            1.0,
            1.0,
            1.0,
            1.0,
            1.0,
            1.0,
            1.0,
            1.0,
            1.0,
            1.0,
            1.0,
            0.0,
            1.0,
            1.0,
            0.0,
            1.0,
            0.0,
            1.0,
            1.0,
            1.0,
            0.0,
            0.0,
            1.0,
            1.0,
            0.0,
            1.0,
            1.0,
            1.0,
            1.0,
            0.0,
            1.0,
            1.0,
            1.0,
            1.0,
            1.0
          ],
          "accepted": [
            true,
            true,
            true,
            true,
            true,
            true,
            true,
            true,
            true,
            true,
            true,
            true,
            true,
            true,
            false,
            true,
            true,
            false,
            true,
            false,
            true,
            true,
            true,
            false,
            false,
            true,
            true,
            false,
            true,
            true,
            true,
            true,
            false,
            true,
            true,
            true,
            true,
            true
          ]
        }
      },
      {
        "locations": [
          [
            "I",
            [
              800,
              7,
              800,
              37
            ]
          ]
        ],
        "test": "3",
        "time": {
          "mcmc": 3.347317695617676,
          "dd": 0
        },
        "paths": {
          "explored": 8,
          "sampled": 23,
          "angelic_found": false,
          "angelic": 0,
          "sample_space_exhausted": true,
          "trials_exhuasted": false,
          "ebits_overflown": false,
          "loc_dd_failed": false,
          "ebits_dd_failed": false,
          "stuck": false,
          "cost": [
            10000020.0,
            10000020.0,
            10000020.0,
            10000020.0,
            10000020.0,
            10000020.0,
            10000020.0,
            10000020.0,
            10000020.0,
            10000020.0,
            10000020.0,
            10000020.0,
            10000020.0,
            10000020.0,
            10000020.0,
            10000020.0,
            10000020.0,
            10000020.0,
            10000020.0,
            10000020.0,
            10000020.0,
            10000020.0
          ],
          "ratio": [
            1.0,
            1.0,
            1.0,
            1.0,
            1.0,
            1.0,
            1.0,
            1.0,
            1.0,
            1.0,
            1.0,
            1.0,
            1.0,
            1.0,
            1.0,
            1.0,
            1.0,
            1.0,
            1.0,
            1.0,
            1.0,
            1.0
          ],
          "accepted": [
            true,
            true,
            true,
            true,
            true,
            true,
            true,
            true,
            true,
            true,
            true,
            true,
            true,
            true,
            true,
            true,
            true,
            true,
            true,
            true,
            true,
            true
          ]
        }
      },
      {
        "locations": [
          [
            "I",
            [
              806,
              8,
              806,
              27
            ]
          ]
        ],
        "test": "3",
        "time": {
          "mcmc": 1.736414909362793,
          "dd": 0
        },
        "paths": {
          "explored": 4,
          "sampled": 6,
          "angelic_found": false,
          "angelic": 0,
          "sample_space_exhausted": true,
          "trials_exhuasted": false,
          "ebits_overflown": false,
          "loc_dd_failed": false,
          "ebits_dd_failed": false,
          "stuck": false,
          "cost": [
            10000020.0,
            10000020.0,
            10000020.0,
            10000020.0,
            10000020.0
          ],
          "ratio": [
            1.0,
            1.0,
            1.0,
            1.0,
            1.0
          ],
          "accepted": [
            true,
            true,
            true,
            true,
            true
          ]
        }
      },
      {
        "locations": [
          [
            "I",
            [
              821,
              6,
              821,
              25
            ]
          ]
        ],
        "test": "3",
        "time": {
          "mcmc": 1.7778120040893555,
          "dd": 0
        },
        "paths": {
          "explored": 4,
          "sampled": 9,
          "angelic_found": false,
          "angelic": 0,
          "sample_space_exhausted": true,
          "trials_exhuasted": false,
          "ebits_overflown": false,
          "loc_dd_failed": false,
          "ebits_dd_failed": false,
          "stuck": false,
          "cost": [
            10000020.0,
            10000020.0,
            10000020.0,
            10000020.0,
            10000020.0,
            10000020.0,
            10000020.0,
            10000020.0
          ],
          "ratio": [
            1.0,
            1.0,
            1.0,
            1.0,
            1.0,
            1.0,
            1.0,
            1.0
          ],
          "accepted": [
            true,
            true,
            true,
            true,
            true,
            true,
            true,
            true
          ]
        }
      },
      {
        "locations": [
          [
            "I",
            [
              1192,
              6,
              1192,
              37
            ]
          ]
        ],
        "test": "3",
        "time": {
          "mcmc": 0.9342246055603027,
          "dd": 0
        },
        "paths": {
          "explored": 2,
          "sampled": 3,
          "angelic_found": false,
          "angelic": 0,
          "sample_space_exhausted": true,
          "trials_exhuasted": false,
          "ebits_overflown": false,
          "loc_dd_failed": false,
          "ebits_dd_failed": false,
          "stuck": false,
          "cost": [
            10000020.0,
            20.0
          ],
          "ratio": [
            1.0,
            1.0
          ],
          "accepted": [
            true,
            true
          ]
        }
      }
    ],
    "symbolic": [],
    "random": []
  }
}